getbookmarks/__init__.py
getbookmarks/bookmark.py
getbookmarks-0.0.3.dist-info/METADATA
getbookmarks-0.0.3.dist-info/WHEEL
getbookmarks-0.0.3.dist-info/top_level.txt
getbookmarks-0.0.3.dist-info/RECORD
