Metadata-Version: 2.1
Name: getbookmarks
Version: 0.0.3
Summary: Get bookmarks from pdf.
Home-page: https://gitlab.com/gpam/services/getbookmarks
Author: Victor Coelho
Author-email: victorhdcoelho@gmail.com
License: UNKNOWN
Platform: UNKNOWN
Classifier: Programming Language :: Python :: 3
Classifier: License :: OSI Approved :: MIT License
Classifier: Operating System :: OS Independent
Requires-Python: >=3.6
Requires-Dist: PyPDF2
